{
    "buildDestination": {
        "destination": "elasticube"
    },
    "datasets": [
        "./31bbed7e-d961-4f36-82f9-d93888b2cf4a/dataset.json",
        "./a3287140-b925-4c77-8806-41d5200c0b5e/dataset.json",
        "./c60e53e1-8a1e-4287-a537-dd68c2010ce4/dataset.json"
    ],
    "experiments": {
    },
    "fiscal": "system",
    "lastSuccessfulManualBuildStartTime": "2023-09-20T14:03:18.790Z",
    "modelStatistics": {
        "enableModelStatistics": false,
        "maxTablesPerCollection": null,
        "recollectStatsInterval": null
    },
    "oid": "86d36672-d90f-4170-bfa2-da38db35c257",
    "relationType": "direct",
    "relations": "./relations.json",
    "relationsTables": [
    ],
    "schemaId": null,
    "title": "nfl",
    "type": "extract"
}
